oneliai/__init__.py
oneliai/client.py
sdk/__init__.py
sdk/client.py
oneliai-1.2.8.dist-info/METADATA
oneliai-1.2.8.dist-info/WHEEL
oneliai-1.2.8.dist-info/top_level.txt
oneliai-1.2.8.dist-info/RECORD
