Metadata-Version: 2.1
Name: oneliai
Version: 1.2.8
Summary: SDK for ONELI.AI Customer API
Author: oneli.ai
Requires-Python: >=3.6
Requires-Dist: requests
